libozone/__init__.py
libozone/priorityqueue/__init__.py
libozone/priorityqueue/heap.py
libozone-1.0.6.dist-info/LICENSE
libozone-1.0.6.dist-info/METADATA
libozone-1.0.6.dist-info/WHEEL
libozone-1.0.6.dist-info/RECORD
