Metadata-Version: 2.1
Name: libozone
Version: 1.0.6
Summary: A collection of data structures written in Python
Home-page: https://libozone.readthedocs.io
License: GPL-3.0 License
Author: Abhijit Sinha
Author-email: grey.shell@gmail.com
Requires-Python: >=3.12,<4.0
Classifier: License :: Other/Proprietary License
Classifier: Programming Language :: Python :: 3
Classifier: Programming Language :: Python :: 3.12
Classifier: Programming Language :: Python :: 3.13
